dfdq/__init__.py
dfdq-0.1.0.dist-info/entry_points.txt
dfdq-0.1.0.dist-info/WHEEL
dfdq-0.1.0.dist-info/METADATA
dfdq-0.1.0.dist-info/RECORD
